setup.py
gauss_bino_distro/Binomialdistribution.py
gauss_bino_distro/Gaussiandistribution.py
gauss_bino_distro/Generaldistribution.py
gauss_bino_distro/__init__.py
gauss_bino_distro.egg-info/PKG-INFO
gauss_bino_distro.egg-info/SOURCES.txt
gauss_bino_distro.egg-info/dependency_links.txt
gauss_bino_distro.egg-info/not-zip-safe
gauss_bino_distro.egg-info/top_level.txt