Metadata-Version: 1.0
Name: gauss-bino-distro
Version: 1.0
Summary: Gaussian and Binomial distributions package
Home-page: UNKNOWN
Author: Gaurav Mishra
Author-email: gaurav.mishra2050@gmail.com
License: UNKNOWN
Platform: UNKNOWN
